sphinx_packaging/__init__.py
sphinx_packaging/peps.py
sphinx_packaging/tconf.py
sphinx_packaging/toml.py
sphinx_packaging-0.3.0.post1.dist-info/LICENSE
sphinx_packaging-0.3.0.post1.dist-info/METADATA
sphinx_packaging-0.3.0.post1.dist-info/WHEEL
sphinx_packaging-0.3.0.post1.dist-info/entry_points.txt
sphinx_packaging-0.3.0.post1.dist-info/RECORD
