Metadata-Version: 2.2
Name: sphinx-packaging
Version: 0.3.0.post1
Summary: A collection of Sphinx utilities related to Python packaging.
Author-email: Dominic Davis-Foster <dominic@davis-foster.co.uk>
License: BSD-3-Clause
Keywords: documentation,packaging,pep,sphinx,sphinx-extension,toml
Home-page: https://github.com/sphinx-toolbox/sphinx-packaging
Project-URL: Issue Tracker, https://github.com/sphinx-toolbox/sphinx-packaging/issues
Project-URL: Source Code, https://github.com/sphinx-toolbox/sphinx-packaging
Project-URL: Documentation, https://sphinx-packaging.readthedocs.io/en/latest
Platform: Windows
Platform: macOS
Platform: Linux
Classifier: Development Status :: 4 - Beta
Classifier: Framework :: Sphinx :: Extension
Classifier: Intended Audience :: Developers
Classifier: License :: OSI Approved :: BSD License
Classifier: Operating System :: OS Independent
Classifier: Programming Language :: Python
Classifier: Programming Language :: Python :: 3 :: Only
Classifier: Programming Language :: Python :: 3.7
Classifier: Programming Language :: Python :: 3.8
Classifier: Programming Language :: Python :: 3.9
Classifier: Programming Language :: Python :: 3.10
Classifier: Programming Language :: Python :: 3.11
Classifier: Programming Language :: Python :: 3.12
Classifier: Programming Language :: Python :: 3.13
Classifier: Programming Language :: Python :: Implementation :: CPython
Classifier: Programming Language :: Python :: Implementation :: PyPy
Classifier: Topic :: Documentation
Classifier: Topic :: Documentation :: Sphinx
Classifier: Topic :: Software Development :: Documentation
Classifier: Topic :: System :: Archiving :: Packaging
Classifier: Topic :: Utilities
Requires-Python: >=3.7
Requires-Dist: docutils>=0.16
Requires-Dist: domdf-python-tools>=3.0.0
Requires-Dist: sphinx>=3.0.3
Requires-Dist: sphinx-jinja2-compat>=0.1.2
